MANIFEST.in
setup.cfg
setup.py
camtono/derivatives/__init__.py
camtono/derivatives/combine.py
camtono/derivatives/features.py
camtono/derivatives/filters.py
camtono/derivatives/generate.py
camtono/derivatives/outputs.py
camtono/derivatives/selects.py
camtono/derivatives/transforms.py
camtono/derivatives_v2/__init__.py
camtono/derivatives_v2/combine.py
camtono/derivatives_v2/generate.py
camtono/derivatives_v2/selects.py
camtono/derivatives_v2/union_query_formatting.py
camtono/derivatives_v3/__init__.py
camtono/derivatives_v3/combine.py
camtono/derivatives_v3/generate.py
camtono/derivatives_v3/selects.py
camtono/derivatives_v3/union_query_formatting.py
camtono_derivatives.egg-info/PKG-INFO
camtono_derivatives.egg-info/SOURCES.txt
camtono_derivatives.egg-info/dependency_links.txt
camtono_derivatives.egg-info/requires.txt
camtono_derivatives.egg-info/top_level.txt