Metadata-Version: 2.1
Name: camtono-derivatives
Version: 1.0.5
Summary: Simplified advertising integrations
Home-page: https://bitbucket.org/adarainc/camtono-derivatives-pkg
Author: DOT
Author-email: dot@adara.com
License: UNKNOWN
Platform: UNKNOWN
Classifier: Programming Language :: Python :: 3
Classifier: License :: OSI Approved :: MIT License
Classifier: Operating System :: OS Independent
Requires-Python: >=3.6
